LICENSE
MANIFEST.in
README.md
requirements.txt
setup.py
tl_radio/__init__.py
tl_radio/__main__.py
tl_radio/example_config.yaml
tl_radio.egg-info/PKG-INFO
tl_radio.egg-info/SOURCES.txt
tl_radio.egg-info/dependency_links.txt
tl_radio.egg-info/requires.txt
tl_radio.egg-info/top_level.txt
tl_radio/config/__init__.py
tl_radio/config/base.py
tl_radio/config/general.py
tl_radio/config/telegram.py
tl_radio/musicplayer/__init__.py
tl_radio/musicplayer/events.py
tl_radio/musicplayer/player.py
tl_radio/musicplayer/playlist.py
tl_radio/musicplayer/song.py
tl_radio/radio/__init__.py
tl_radio/radio/events.py
tl_radio/radio/radio.py
tl_radio/radio/station.py
tl_radio/sql/__init__.py
tl_radio/sql/sql_telethon.py
tl_radio/sql/sql_youtubedl.py
tl_radio/utils/__init__.py
tl_radio/utils/commandhandler.py
tl_radio/utils/run_in_executor.py