Metadata-Version: 2.1
Name: tl-radio
Version: 0.0.5
Summary: Telegram UserBot to play and stream audio to telegram group chat using YoutubeDl and TgCalls.
Home-page: https://github.com/nitanmarcel/tl_radio
Author: Marcel Alexandru Nitan
Author-email: nitan.marcel@gamil.com
License: UNKNOWN
Platform: UNKNOWN
Classifier: Development Status :: 4 - Beta
Classifier: License :: OSI Approved :: GNU General Public License v3 (GPLv3)
Classifier: Topic :: Communications :: Chat
Classifier: Framework :: AsyncIO
Classifier: Programming Language :: Python
Classifier: Programming Language :: Python :: 3
Classifier: Programming Language :: Python :: 3.7
Classifier: Programming Language :: Python :: 3.8
Classifier: Programming Language :: Python :: 3.9
Requires-Python: ~=3.7
